agentflux/__init__.py
agentflux/agent_manager.cpython-312-x86_64-linux-gnu.so
agentflux/logger.cpython-312-x86_64-linux-gnu.so
agentflux/qagent_manager.cpython-312-x86_64-linux-gnu.so
agentflux/core/__init__.py
agentflux/core/agent_app.cpython-312-x86_64-linux-gnu.so
agentflux/core/function_request.cpython-312-x86_64-linux-gnu.so
agentflux/core/qagent_app.cpython-312-x86_64-linux-gnu.so
agentflux/core/apps/__init__.py
agentflux/core/apps/app_dsl_service.cpython-312-x86_64-linux-gnu.so
agentflux/core/llms/__init__.py
agentflux/core/llms/llm.cpython-312-x86_64-linux-gnu.so
agentflux/core/llms/vllm.cpython-312-x86_64-linux-gnu.so
agentflux/core/template/qagent.cpython-312-x86_64-linux-gnu.so
agentflux/core/tools/__init__.py
agentflux/core/tools/api_tool.cpython-312-x86_64-linux-gnu.so
agentflux/core/tools/parser.cpython-312-x86_64-linux-gnu.so
agentflux/core/tools/ssrf_proxy.cpython-312-x86_64-linux-gnu.so
agentflux/core/tools/tool.cpython-312-x86_64-linux-gnu.so
agentflux/core/tools/tool_bundle.cpython-312-x86_64-linux-gnu.so
agentflux/core/tools/tool_entities.cpython-312-x86_64-linux-gnu.so
agentflux/data/base/template.yml
agentflux/data/base/template_agent.yml
agentflux/data/base/template_tool.json
agentflux/manage/agent_create.cpython-312-x86_64-linux-gnu.so
agentflux/manage/tool_create.cpython-312-x86_64-linux-gnu.so
agentflux/utils/__init__.py
agentflux/utils/agent_file_db.cpython-312-x86_64-linux-gnu.so
agentflux/utils/cython_wraper.cpython-312-x86_64-linux-gnu.so
agentflux/utils/file_db.cpython-312-x86_64-linux-gnu.so
agentflux/utils/json_utils.cpython-312-x86_64-linux-gnu.so
agentflux/utils/yml_utils.cpython-312-x86_64-linux-gnu.so
agentflux-0.0.1.4.dist-info/METADATA
agentflux-0.0.1.4.dist-info/WHEEL
agentflux-0.0.1.4.dist-info/top_level.txt
agentflux-0.0.1.4.dist-info/zip-safe
agentflux-0.0.1.4.dist-info/RECORD
